{"approval_requested":0,"approved":1,"beaming":"0","database_id":1414,"db_version":1,"deleted":0,"description":"Switch Sensor Cover","device_ref":"4002:0001","exclusion":"<p>Triple click on operating surface.<br><\/p>","first_approval_time":"2021-09-18 20:40:25","frequently_listening":"0","inclusion":"<p>Triple click on operating surface.<br><\/p>","label":"50x4xx","last_approval_time":"2021-09-18 20:40:25","listening":"1","overview":"<p>The sensor cover contains a radio receiver. Using the connected transmitters, you can switch connected ohmic and complex loads (such as incandescent lamps, low voltage halogen lamps) using the relay switch insert.<\/p>","protocol_version":"2.028","routing":"1","usage":"<p><br><\/p>","uuid":"50x4xx","version_max":"255.255","version_min":"0.000","wakeup":"<p>Triple click on operating surface.<\/p>","manufacturer":{"id":12,"label":"Merten","reference":122,"uuid":"merten","url":""},"category":{"id":21,"label":"Wall Switch","category":"WallSwitch","description":"Any device attached to the wall that controls a binary status of something, for ex. a light switch"},"endpoints":[{"id":2256,"number":0,"label":"Endpoint 0","basic_class":{"id":4,"name":"BASIC_TYPE_ROUTING_SLAVE"},"generic_class":{"id":16,"name":"GENERIC_TYPE_SWITCH_BINARY"},"specific_class":{"id":1,"name":"SPECIFIC_TYPE_POWER_SWITCH_BINARY"},"commandclass":[{"cmdclass_id":22880,"commandclass_name":"COMMAND_CLASS_NO_OPERATION","basic":"0","version":1,"nif":"","secure":"","nonsecure":"1","config":"","command_group":"MGMT","channels":[]},{"cmdclass_id":22882,"commandclass_name":"COMMAND_CLASS_BASIC","basic":"0","version":1,"nif":"","secure":"","nonsecure":"1","config":"","command_group":"APP","channels":[]},{"cmdclass_id":22879,"commandclass_name":"COMMAND_CLASS_SWITCH_BINARY","basic":"0","version":1,"nif":"1","secure":"","nonsecure":"1","config":"","command_group":"APP","channels":[{"name":"switch_binary","config":"","label":"Switch","overview":"","deprecated":"0000-00-00","id":6382,"options":[]}]},{"cmdclass_id":22875,"commandclass_name":"COMMAND_CLASS_SWITCH_ALL","basic":"0","version":1,"nif":"1","secure":"","nonsecure":"1","config":"","command_group":"","channels":[]},{"cmdclass_id":22874,"commandclass_name":"COMMAND_CLASS_SWITCH_TOGGLE_BINARY","basic":"0","version":1,"nif":"1","secure":"","nonsecure":"1","config":"","command_group":"APP","channels":[]},{"cmdclass_id":22873,"commandclass_name":"COMMAND_CLASS_CONFIGURATION","basic":"0","version":1,"nif":"1","secure":"","nonsecure":"1","config":"","command_group":"APP","channels":[]},{"cmdclass_id":22881,"commandclass_name":"COMMAND_CLASS_MANUFACTURER_SPECIFIC","basic":"0","version":1,"nif":"1","secure":"","nonsecure":"1","config":"","command_group":"MGMT","channels":[]},{"cmdclass_id":22877,"commandclass_name":"COMMAND_CLASS_PROTECTION","basic":"0","version":2,"nif":"1","secure":"","nonsecure":"1","config":"","command_group":"APP","channels":[]},{"cmdclass_id":22876,"commandclass_name":"COMMAND_CLASS_ASSOCIATION","basic":"0","version":1,"nif":"1","secure":"","nonsecure":"1","config":"","command_group":"MGMT","channels":[]},{"cmdclass_id":22878,"commandclass_name":"COMMAND_CLASS_VERSION","basic":"0","version":1,"nif":"1","secure":"","nonsecure":"1","config":"","command_group":"MGMT","channels":[]},{"cmdclass_id":22872,"commandclass_name":"COMMAND_CLASS_MULTI_CHANNEL_ASSOCIATION","basic":"0","version":1,"nif":"1","secure":"","nonsecure":"1","config":"","command_group":"MGMT","channels":[]}]}],"parameters":[],"associations":[{"group_id":1,"label":"Switching additional devices","max_nodes":1,"controller":"0","description":"Switching additional radio receivers","overview":"<p >Switching additional radio receivers<\/p>","id":3164},{"group_id":2,"label":"unknown","max_nodes":1,"controller":"0","description":"unknown","overview":"<p>unknown, not mentioned in the manual<br><\/p>","id":3165}],"documents":[{"id":3320,"file":"5024xx_HW_DE.pdf","label":"Manual"},{"id":3321,"file":"50x4xx.jpg","label":"Image"}]}