{"approval_requested":0,"approved":1,"beaming":"1","database_id":428,"db_version":1,"deleted":0,"description":"Door\/Window Contact","device_ref":"0001:0001","exclusion":"<p>Pressing tamper switch three times\u00a0within 1.5 second will enter\u00a0exclusion mode.<\/p>","first_approval_time":"2017-09-18 22:34:45","frequently_listening":"0","inclusion":"<p>Pressing tamper switch three times\u00a0within 1.5 second will enter inclusion\u00a0mode.<\/p>","label":"SM103","last_approval_time":"2019-08-04 17:09:39","listening":"0","overview":"<p>The Door\/Window Detector is a Z-WaveTM enabled device and is fully compatiblewith any Z-WaveTM enabled network. Z-WaveTM enabled\u00a0 devices displaying the\u00a0Z-WaveTM logo can also be used with it regardless of the manufacturer, and ours\u00a0can also be used in other manufacturer\u2019s Z-WaveTM enabled networks. Inclusion\u00a0of this Door\/Window Detector on other manufacturer\u2019s Wireless Controller menu\u00a0allows remote turn-on of connected modules and their connected lighting when the\u00a0Detector is triggered.<\/p>","protocol_version":"2.064","routing":"1","usage":"","uuid":"sm103","version_max":"255.255","version_min":"0.000","wakeup":"<ol><li>The unit will stay \u201cawake\u201d for ten minutes when power is first supplied to allow\u00a0time for configuration.<\/li> <li>After the unit stays in sleep status, it can be woken up by pressing the tamper\u00a0switch continuously until the LED lights up once. The unit will enter sleep status\u00a0again after 10 seconds. If longer awake is desired, press tamper switch three\u00a0times within 1.5 seconds will prolong its awake period to 10 minutes.<\/li> <\/ol>","manufacturer":{"id":67,"label":"Chromagic Technologies Corporation","reference":278,"uuid":"chromagic","url":"http:\/\/www.ctc-chromagic.com\/"},"category":{"id":18,"label":"Sensor","category":"Sensor","description":"Device used to measure something"},"endpoints":[{"id":492,"number":0,"label":"Endpoint 0","basic_class":{"id":4,"name":"BASIC_TYPE_ROUTING_SLAVE"},"generic_class":{"id":32,"name":"GENERIC_TYPE_SENSOR_BINARY"},"specific_class":{"id":1,"name":"SPECIFIC_TYPE_ROUTING_SENSOR_BINARY"},"commandclass":[{"cmdclass_id":4211,"commandclass_name":"COMMAND_CLASS_NO_OPERATION","basic":"0","version":1,"nif":"","secure":"","nonsecure":"1","config":"","command_group":"MGMT","channels":[]},{"cmdclass_id":4217,"commandclass_name":"COMMAND_CLASS_BASIC","basic":"0","version":1,"nif":"1","secure":"","nonsecure":"1","config":"","command_group":"APP","channels":[]},{"cmdclass_id":4220,"commandclass_name":"COMMAND_CLASS_SENSOR_BINARY","basic":"1","version":1,"nif":"1","secure":"0","nonsecure":"1","config":"","command_group":"APP","channels":[{"name":"sensor_binary","config":"","label":"Binary Sensor","overview":"","deprecated":"0000-00-00","id":1227,"options":[]}]},{"cmdclass_id":4213,"commandclass_name":"COMMAND_CLASS_CONFIGURATION","basic":"0","version":1,"nif":"1","secure":"","nonsecure":"1","config":"","command_group":"APP","channels":[]},{"cmdclass_id":4216,"commandclass_name":"COMMAND_CLASS_ALARM","basic":"0","version":1,"nif":"1","secure":"","nonsecure":"1","config":"","command_group":"APP","channels":[{"name":"alarm_general","config":"","label":"Alarm","overview":"","deprecated":"0000-00-00","id":1226,"options":[]}]},{"cmdclass_id":4218,"commandclass_name":"COMMAND_CLASS_MANUFACTURER_SPECIFIC","basic":"0","version":1,"nif":"1","secure":"","nonsecure":"1","config":"","command_group":"MGMT","channels":[]},{"cmdclass_id":4214,"commandclass_name":"COMMAND_CLASS_BATTERY","basic":"0","version":1,"nif":"1","secure":"","nonsecure":"1","config":"","command_group":"MGMT","channels":[]},{"cmdclass_id":4219,"commandclass_name":"COMMAND_CLASS_WAKE_UP","basic":"0","version":1,"nif":"1","secure":"","nonsecure":"1","config":"","command_group":"MGMT","channels":[]},{"cmdclass_id":4215,"commandclass_name":"COMMAND_CLASS_ASSOCIATION","basic":"0","version":1,"nif":"1","secure":"","nonsecure":"1","config":"","command_group":"MGMT","channels":[]},{"cmdclass_id":4212,"commandclass_name":"COMMAND_CLASS_VERSION","basic":"0","version":1,"nif":"1","secure":"","nonsecure":"1","config":"","command_group":"MGMT","channels":[]}]}],"parameters":[{"param_id":1,"label":"Basic Set Level","description":"Value to be sent with a BASIC SET command","units":"","overview":"","size":1,"bitmask":0,"default":99,"minimum":0,"maximum":99,"read_only":"","write_only":"","reinclude":0,"limit_options":"","advanced":0,"confirmation":0,"id":2673,"options":[]},{"param_id":2,"label":"Configuring the OFF Delay","description":"OFF Delay in seconds ","units":"","overview":"","size":1,"bitmask":0,"default":1,"minimum":0,"maximum":127,"read_only":"","write_only":"","reinclude":0,"limit_options":"","advanced":0,"confirmation":0,"id":2674,"options":[]}],"associations":[{"group_id":1,"label":"Tamper Event Report (Alarm Report)","max_nodes":5,"controller":"1","description":"","overview":"","id":757},{"group_id":2,"label":"Control other Z-Wave Devices","max_nodes":5,"controller":"1","description":"","overview":"","id":758}],"documents":[{"id":510,"file":"sm103.png","label":"Product Image"},{"id":2234,"file":"Everspring-SM103-ContattoMagnetico.pdf","label":"Manual"}]}