{"approval_requested":0,"approved":1,"beaming":"1","database_id":698,"db_version":1,"deleted":0,"description":"Wall Plug with dimming function","device_ref":"6942:4503","exclusion":"<p>Press and hold the push button for 4 seconds and release to start the inclusion or exclusion process<\/p>","first_approval_time":"2017-09-30 16:14:41","frequently_listening":"0","inclusion":"<ol><li> <p>Make sure your Z\u2010Wave controller is in the right operation mode (include or exclude).<\/p> <\/li> <li> <p>Press and hold the push button for 4 seconds and release to start the inclusion or exclusion process<\/p> <p>(indication mode: Ready for learn mode).<\/p> <\/li> <li> <p>(The product will start NWI automatically after unsuccessful normal inclusion)\u00a0<\/p> <\/li> <\/ol>","label":"iPlugDim","last_approval_time":"2019-10-06 05:15:24","listening":"1","overview":"<ul><li>The iPlugDim can be remotely controlled.<\/li> <li>The iPlugDim can be controlled by the push button on the front of the device.<\/li> <li>The iPlugDim \u2019s indicator light will indicate the status of the switch (ON or OFF).<\/li> <li>The iPlugDim can make a dimming function of the load.<\/li> <\/ul><p>Press and release the push button of the iPlugDim to switch on\/off the load of socket, press and hold the push button to dim the load of the socket.<\/p> <p><strong>Indication modes <br \/><\/strong><\/p> <p>The indicator gives various statuses of the device as follows:<\/p> <ol><li>Ready for learn mode:\u00a0Indicator light blinks every second.<\/li> <li>Learn in progress (add):\u00a0Indicator light blinks 2 times every second.<\/li> <li>Learn in progress (remove): Indicator light blinks 3 times every second.<\/li> <li>Learn mode success: Indicator light is on for second.<\/li> <li>Learn mode failed: Indicator light blinks 8 times fast.<\/li> <\/ol>","protocol_version":"2.097","routing":"1","usage":"","uuid":"iplugdim","version_max":"255.255","version_min":"0.000","wakeup":"","manufacturer":{"id":37,"label":"Wintop","reference":151,"uuid":"wintop","url":""},"category":{"id":15,"label":"Power Outlet","category":"PowerOutlet","description":"Small devices to be plugged into a power socket in a wall which stick there"},"endpoints":[{"id":960,"number":0,"label":"Endpoint 0","basic_class":{"id":4,"name":"BASIC_TYPE_ROUTING_SLAVE"},"generic_class":{"id":17,"name":"GENERIC_TYPE_SWITCH_MULTILEVEL"},"specific_class":{"id":1,"name":"SPECIFIC_TYPE_POWER_SWITCH_MULTILEVEL"},"commandclass":[{"cmdclass_id":8754,"commandclass_name":"COMMAND_CLASS_NO_OPERATION","basic":"0","version":1,"nif":"","secure":"","nonsecure":"1","config":"","command_group":"MGMT","channels":[]},{"cmdclass_id":8755,"commandclass_name":"COMMAND_CLASS_BASIC","basic":"0","version":1,"nif":"","secure":"","nonsecure":"1","config":"","command_group":"APP","channels":[]},{"cmdclass_id":8752,"commandclass_name":"COMMAND_CLASS_SWITCH_MULTILEVEL","basic":"1","version":1,"nif":"1","secure":"","nonsecure":"1","config":"","command_group":"APP","channels":[{"name":"switch_dimmer","config":"","label":"Dimmer","overview":"","deprecated":"0000-00-00","id":2561,"options":[]}]},{"cmdclass_id":8751,"commandclass_name":"COMMAND_CLASS_SWITCH_ALL","basic":"0","version":1,"nif":"1","secure":"","nonsecure":"1","config":"","command_group":"","channels":[]},{"cmdclass_id":8758,"commandclass_name":"COMMAND_CLASS_CONFIGURATION","basic":"","version":0,"nif":"1","secure":"","nonsecure":"1","config":"","command_group":"APP","channels":[]},{"cmdclass_id":8753,"commandclass_name":"COMMAND_CLASS_MANUFACTURER_SPECIFIC","basic":"0","version":1,"nif":"1","secure":"","nonsecure":"1","config":"","command_group":"MGMT","channels":[]},{"cmdclass_id":8757,"commandclass_name":"COMMAND_CLASS_POWERLEVEL","basic":"0","version":1,"nif":"1","secure":"","nonsecure":"1","config":"","command_group":"MGMT","channels":[]},{"cmdclass_id":8756,"commandclass_name":"COMMAND_CLASS_VERSION","basic":"0","version":1,"nif":"1","secure":"","nonsecure":"1","config":"","command_group":"MGMT","channels":[]}]}],"parameters":[{"param_id":1,"label":"Set to Default","description":"Set to Default","units":"","overview":"","size":1,"bitmask":0,"default":85,"minimum":0,"maximum":255,"read_only":"0","write_only":"0","reinclude":0,"limit_options":"1","advanced":0,"confirmation":1,"id":7405,"options":[{"value":1,"label":"Set all config values to default values ","id":10136}]}],"associations":[],"documents":[{"id":988,"file":"iplugdim.pdf","label":"iPlugDim Manual"},{"id":2545,"file":"iPlugDim.jpg","label":"Image"}]}