{"approval_requested":0,"approved":1,"beaming":"1","database_id":954,"db_version":2,"deleted":0,"description":"Single relay switch","device_ref":"0001:0101","exclusion":"<p>When prompted by your primary controller, press the button<\/p>","first_approval_time":"0000-00-00 00:00:00","frequently_listening":"0","inclusion":"<p>When prompted by your primary controller, press the button<\/p>","label":"ZSL301EU","last_approval_time":"2019-09-19 18:04:32","listening":"1","overview":"<p>Switch Link is a power ON\/OFF module purposed to control lighting lamps or motor loads.<\/p>","protocol_version":"2.051","routing":"1","usage":"","uuid":"zsl301eu","version_max":"255.255","version_min":"0.000","wakeup":"","manufacturer":{"id":607,"label":"Team Precision PCL","reference":137,"uuid":"precision","url":""},"category":{"id":21,"label":"Wall Switch","category":"WallSwitch","description":"Any device attached to the wall that controls a binary status of something, for ex. a light switch"},"endpoints":[{"id":1443,"number":0,"label":"Endpoint 0","basic_class":{"id":3,"name":"BASIC_TYPE_SLAVE"},"generic_class":{"id":16,"name":"GENERIC_TYPE_SWITCH_BINARY"},"specific_class":{"id":1,"name":"SPECIFIC_TYPE_POWER_SWITCH_BINARY"},"commandclass":[{"cmdclass_id":13671,"commandclass_name":"COMMAND_CLASS_NO_OPERATION","basic":"0","version":1,"nif":"","secure":"","nonsecure":"1","config":"","command_group":"MGMT","channels":[]},{"cmdclass_id":13664,"commandclass_name":"COMMAND_CLASS_BASIC","basic":"0","version":1,"nif":"","secure":"","nonsecure":"1","config":"","command_group":"APP","channels":[]},{"cmdclass_id":13665,"commandclass_name":"COMMAND_CLASS_SWITCH_BINARY","basic":"0","version":1,"nif":"","secure":"","nonsecure":"1","config":"","command_group":"APP","channels":[{"name":"switch_binary","config":"","label":"Switch","overview":"","deprecated":"0000-00-00","id":3877,"options":[]}]},{"cmdclass_id":13670,"commandclass_name":"COMMAND_CLASS_SWITCH_ALL","basic":"0","version":1,"nif":"","secure":"","nonsecure":"1","config":"","command_group":"","channels":[]},{"cmdclass_id":13668,"commandclass_name":"COMMAND_CLASS_SCENE_ACTIVATION","basic":"0","version":1,"nif":"","secure":"","nonsecure":"1","config":"","command_group":"APP","channels":[{"name":"scene_number","config":"","label":"Scene Number","overview":"","deprecated":"0000-00-00","id":3878,"options":[]}]},{"cmdclass_id":13673,"commandclass_name":"COMMAND_CLASS_SCENE_ACTUATOR_CONF","basic":"0","version":1,"nif":"","secure":"","nonsecure":"1","config":"","command_group":"APP","channels":[]},{"cmdclass_id":13672,"commandclass_name":"COMMAND_CLASS_CONFIGURATION","basic":"0","version":1,"nif":"","secure":"","nonsecure":"1","config":"","command_group":"APP","channels":[]},{"cmdclass_id":13667,"commandclass_name":"COMMAND_CLASS_MANUFACTURER_SPECIFIC","basic":"0","version":1,"nif":"","secure":"","nonsecure":"1","config":"","command_group":"MGMT","channels":[]},{"cmdclass_id":13666,"commandclass_name":"COMMAND_CLASS_PROTECTION","basic":"0","version":1,"nif":"","secure":"","nonsecure":"1","config":"","command_group":"APP","channels":[]},{"cmdclass_id":13669,"commandclass_name":"COMMAND_CLASS_VERSION","basic":"0","version":1,"nif":"","secure":"","nonsecure":"1","config":"","command_group":"MGMT","channels":[]}]}],"parameters":[{"param_id":0,"label":"Last Status","description":"Last Status","units":"","overview":"","size":1,"bitmask":0,"default":0,"minimum":0,"maximum":2,"read_only":"0","write_only":"0","reinclude":0,"limit_options":"0","advanced":0,"confirmation":0,"id":7238,"options":[{"value":0,"label":"Resume after power outage","id":9880},{"value":1,"label":"ON after power outage","id":9881},{"value":2,"label":"OFF after power outage","id":9882}]},{"param_id":1,"label":"Night Light","description":"Night Light","units":"","overview":"","size":1,"bitmask":0,"default":1,"minimum":0,"maximum":1,"read_only":"0","write_only":"0","reinclude":0,"limit_options":"0","advanced":0,"confirmation":0,"id":7239,"options":[{"value":0,"label":"LED ON when light ON","id":9883},{"value":1,"label":"LED ON when light OFF","id":9884}]},{"param_id":2,"label":"Enable LED","description":"Enable LED","units":"","overview":"","size":1,"bitmask":0,"default":1,"minimum":0,"maximum":1,"read_only":"0","write_only":"0","reinclude":0,"limit_options":"0","advanced":0,"confirmation":0,"id":7240,"options":[{"value":0,"label":"Disable LED","id":9885},{"value":1,"label":"Enable LED","id":9886}]},{"param_id":3,"label":"Enable All ON\/All OFF","description":"Enable All ON\/All OFF","units":"","overview":"","size":1,"bitmask":0,"default":-1,"minimum":-1,"maximum":2,"read_only":"0","write_only":"0","reinclude":0,"limit_options":"0","advanced":0,"confirmation":0,"id":7241,"options":[{"value":-1,"label":"Enable both All ON and All OFF command","id":9887},{"value":0,"label":"Disable both All ON and All OFF command.","id":9888},{"value":1,"label":"Enable only All OFF command.","id":9889},{"value":2,"label":"Enable only All ON command.","id":9890}]},{"param_id":4,"label":"Button Protection","description":"Button Protection","units":"","overview":"","size":1,"bitmask":0,"default":0,"minimum":0,"maximum":2,"read_only":"0","write_only":"0","reinclude":0,"limit_options":"0","advanced":1,"confirmation":1,"id":7242,"options":[{"value":0,"label":"User can use button for ON\/OFF manual control.","id":9891},{"value":1,"label":"Protect Mode","id":9892},{"value":2,"label":"Disable button from manual control.","id":9893}]},{"param_id":5,"label":"Delay In Time","description":"Delay In Time","units":"seconds","overview":"<p>0 \u00a0 -&gt;\u00a0 The light will be ON instantaneously once ON command is received.<\/p> <p>1 - 5 \u00a0 -&gt;\u00a0 The module will detain the ON process for 1-5 seconds up to user preferences.<\/p>","size":1,"bitmask":0,"default":0,"minimum":0,"maximum":5,"read_only":"0","write_only":"0","reinclude":0,"limit_options":"0","advanced":0,"confirmation":0,"id":7243,"options":[]},{"param_id":6,"label":"Delay Out Time","description":"Delay Out Time","units":"seconds","overview":"<p>0 \u00a0 -&gt;\u00a0 The light will be OFF instantaneously once OFF command is received.<\/p> <p>1 - 5 \u00a0 -&gt;\u00a0 The module will detain the OFF process for 1-5 seconds up to user preferences.<\/p>","size":1,"bitmask":0,"default":0,"minimum":0,"maximum":5,"read_only":"0","write_only":"0","reinclude":0,"limit_options":"0","advanced":0,"confirmation":0,"id":7244,"options":[]}],"associations":[],"documents":[{"id":1820,"file":"zslphoto.jpg","label":"Product photo"},{"id":1821,"file":"ZSL301EU-manual.pdf","label":"Installation - user manual"}]}