{"approval_requested":0,"approved":1,"beaming":"1","database_id":976,"db_version":5,"deleted":0,"description":"Z-Wave Plug-in Smart Dimmer","device_ref":"5044:3033","exclusion":"<p>Press and release the manual\/program button.<\/p>","first_approval_time":"0000-00-00 00:00:00","frequently_listening":"0","inclusion":"<p>Press and release the manual\/program button. (Tested to work with Network Wide Inclusion.)<\/p>","label":"39339 (ZW3107) ","last_approval_time":"2020-12-20 21:04:26","listening":"1","overview":"<p>Stay connected to your home with a Honeywell Z-Wave Smart Dimmer. Compatible with all Z\u2011Wave certified gateways, the smart dimmer gives you wireless control of your dimmable lights from any mobile device, computer or Z-Wave enabled remote. Setup is easy \u2013 simply plug the dimmer into any in-wall outlet, then connect your light to one of the two dual smart outlets located on either side of the dimmer. Whether you\u2019re at home or away, access the dimmer to turn your lights on and off, or to adjust the brightness levels of the room.<\/p> <p>The smart dimmer incorporates reliable, dynamic illumination to your home, giving you a fully lit workspace or letting you settle down for the evening with effective, stylish accent lighting. Not only does the smart dimmer help cut energy costs, but it boosts the safety of your home by keeping rooms looking bright and lived\u2011in. Give your space the perfect amount of light with a Honeywell Z-Wave Smart Dimmer.<\/p> <h4>Features<\/h4> <ul><li>ALEXA COMPATIBLE (HUB REQUIRED) - Requires an Alexa supported hub for voice control with Amazon Echo Products (Alexa device and hub are sold separately).Cannot connect directly with ECHO PLUS (Only ZigBee products can connect directly to Echo Plus)<\/li> <li>REQUIRES A Z-WAVE CERTIFIED HUB - Compatible with the following Z-Wave Hubs: Honeywell, SmartThings, Pulse, Trane, Wink, Nexia, Honeywell, HomeSeer, Smart Security, Harmony Home Hub Extender, Vera, and Fibaro<\/li> <li>WIRELESSLY CONTROL &amp; SCHEDULE LIGHTS - Schedule timed events for connected lighting. Customize scenes for day or night, home or away. Wirelessly control from anywhere through your smartphone, tablet, PC or Z-Wave remote<\/li> <li>FULL RANGE DIMMING \u2013 Give your space the perfect amount of light with the ability to customize the brightness levels from 0 to 100%. Works ONLY with dimmable bulbs and lamps<\/li> <li>2 SIMULTANEOUSLY CONTROLLED POLARIZED OUTLET - features 2 polarized outlets that can be controlled at the same time (NOT SEPERATLEY) and a manual ON\/OFF, dim &amp; program physical button. To setup simply plug the module into any in-wall outlet, then connect<\/li> <\/ul>","protocol_version":"4.034","routing":"1","usage":"","uuid":"39339","version_max":"255.255","version_min":"0.000","wakeup":"","manufacturer":{"id":27,"label":"Honeywell","reference":57,"uuid":"honeywell","url":""},"category":{"id":15,"label":"Power Outlet","category":"PowerOutlet","description":"Small devices to be plugged into a power socket in a wall which stick there"},"endpoints":[{"id":1475,"number":0,"label":"Endpoint 0","basic_class":{"id":4,"name":"BASIC_TYPE_ROUTING_SLAVE"},"generic_class":{"id":17,"name":"GENERIC_TYPE_SWITCH_MULTILEVEL"},"specific_class":{"id":1,"name":"SPECIFIC_TYPE_POWER_SWITCH_MULTILEVEL"},"commandclass":[{"cmdclass_id":13975,"commandclass_name":"COMMAND_CLASS_NO_OPERATION","basic":"0","version":1,"nif":"","secure":"","nonsecure":"1","config":"","command_group":"MGMT","channels":[]},{"cmdclass_id":13982,"commandclass_name":"COMMAND_CLASS_BASIC","basic":"0","version":1,"nif":"","secure":"","nonsecure":"1","config":"","command_group":"APP","channels":[]},{"cmdclass_id":13984,"commandclass_name":"COMMAND_CLASS_SWITCH_MULTILEVEL","basic":"1","version":2,"nif":"1","secure":"0","nonsecure":"1","config":"","command_group":"APP","channels":[{"name":"switch_dimmer","config":"","label":"Dimmer","overview":"","deprecated":"0000-00-00","id":3955,"options":[]}]},{"cmdclass_id":13977,"commandclass_name":"COMMAND_CLASS_SWITCH_ALL","basic":"0","version":1,"nif":"1","secure":"","nonsecure":"1","config":"","command_group":"","channels":[]},{"cmdclass_id":13973,"commandclass_name":"COMMAND_CLASS_SCENE_ACTIVATION","basic":"0","version":1,"nif":"1","secure":"","nonsecure":"1","config":"","command_group":"APP","channels":[{"name":"scene_number","config":"","label":"Scene Number","overview":"","deprecated":"0000-00-00","id":3954,"options":[]}]},{"cmdclass_id":13971,"commandclass_name":"COMMAND_CLASS_SCENE_ACTUATOR_CONF","basic":"0","version":1,"nif":"1","secure":"","nonsecure":"1","config":"","command_group":"APP","channels":[]},{"cmdclass_id":13981,"commandclass_name":"COMMAND_CLASS_CRC_16_ENCAP","basic":"0","version":1,"nif":"1","secure":"","nonsecure":"1","config":"","command_group":"ENCAP","channels":[]},{"cmdclass_id":13972,"commandclass_name":"COMMAND_CLASS_ASSOCIATION_GRP_INFO","basic":"0","version":1,"nif":"1","secure":"","nonsecure":"1","config":"","command_group":"MGMT","channels":[]},{"cmdclass_id":13976,"commandclass_name":"COMMAND_CLASS_DEVICE_RESET_LOCALLY","basic":"0","version":1,"nif":"1","secure":"","nonsecure":"1","config":"","command_group":"MGMT","channels":[]},{"cmdclass_id":13979,"commandclass_name":"COMMAND_CLASS_ZWAVEPLUS_INFO","basic":"0","version":1,"nif":"1","secure":"","nonsecure":"1","config":"","command_group":"MGMT","channels":[]},{"cmdclass_id":13980,"commandclass_name":"COMMAND_CLASS_CONFIGURATION","basic":"0","version":1,"nif":"1","secure":"","nonsecure":"1","config":"","command_group":"APP","channels":[]},{"cmdclass_id":13985,"commandclass_name":"COMMAND_CLASS_MANUFACTURER_SPECIFIC","basic":"0","version":1,"nif":"1","secure":"","nonsecure":"1","config":"","command_group":"MGMT","channels":[]},{"cmdclass_id":13983,"commandclass_name":"COMMAND_CLASS_POWERLEVEL","basic":"0","version":1,"nif":"1","secure":"","nonsecure":"1","config":"","command_group":"MGMT","channels":[]},{"cmdclass_id":13974,"commandclass_name":"COMMAND_CLASS_FIRMWARE_UPDATE_MD","basic":"0","version":1,"nif":"1","secure":"","nonsecure":"1","config":"","command_group":"MGMT","channels":[]},{"cmdclass_id":13970,"commandclass_name":"COMMAND_CLASS_ASSOCIATION","basic":"0","version":2,"nif":"1","secure":"","nonsecure":"1","config":"","command_group":"MGMT","channels":[]},{"cmdclass_id":13978,"commandclass_name":"COMMAND_CLASS_VERSION","basic":"0","version":2,"nif":"1","secure":"","nonsecure":"1","config":"","command_group":"MGMT","channels":[]}]}],"parameters":[{"param_id":3,"label":"LED Light","description":"LED Light Control","units":"","overview":"<p>When shipped from the factory, the LED is set to turn ON when the connected light is turned On. This is the default setting and can be changed if your primary controller supports the node configuration function or by a manual method. To make the LED turn ON when the light is turned ON, change parameter 3s value to 1. To turn the LED OFF at all times, change parameter 3s value to 2.<\/p>","size":1,"bitmask":0,"default":0,"minimum":0,"maximum":2,"read_only":"0","write_only":"0","reinclude":0,"limit_options":"0","advanced":0,"confirmation":0,"id":5706,"options":[{"value":0,"label":"Set parameter to factory default","id":8094},{"value":1,"label":"LED On when light is turned On ","id":8095},{"value":2,"label":"LED always Off","id":8096}]},{"param_id":6,"label":"Dim Up\/Down Behavior","description":"Controls whether level changes are instant or smooth","units":"","overview":"<p >This is an undocumented feature. This parameter allows you to choose between instant level changes and smooth level changes on newer Jasco\/Honeywell\/GE dimmers. This feature should work on dimmers that come out of the box with instant level changes, it may not work on older dimmers that smoothly change levels by default. <br><\/p>","size":1,"bitmask":0,"default":0,"minimum":0,"maximum":1,"read_only":"0","write_only":"0","reinclude":0,"limit_options":"1","advanced":0,"confirmation":0,"id":9120,"options":[{"value":0,"label":"Instant Level Changes","id":12308},{"value":1,"label":"Smooth Level Changes","id":12309}]},{"param_id":7,"label":"Dim Rate Adjustments (Z-Wave Controller)","description":"Number of steps or levels ","units":"","overview":"","size":1,"bitmask":0,"default":1,"minimum":1,"maximum":99,"read_only":"0","write_only":"0","reinclude":0,"limit_options":"0","advanced":0,"confirmation":0,"id":5707,"options":[]},{"param_id":8,"label":"Dim Rate Adjustments (Z-Wave Controller, Timing) ","description":"Timing of steps","units":"","overview":"","size":2,"bitmask":0,"default":3,"minimum":1,"maximum":255,"read_only":"0","write_only":"0","reinclude":0,"limit_options":"0","advanced":0,"confirmation":0,"id":5708,"options":[]},{"param_id":9,"label":"Dim Rate Adjustments (manually controlled) ","description":"Number of steps or levels","units":"","overview":"","size":1,"bitmask":0,"default":1,"minimum":1,"maximum":99,"read_only":"0","write_only":"0","reinclude":0,"limit_options":"0","advanced":0,"confirmation":0,"id":5709,"options":[]},{"param_id":10,"label":"Dim Rate Adjustments (manually controlled, timing)","description":"Timing of steps","units":"","overview":"","size":2,"bitmask":0,"default":3,"minimum":0,"maximum":255,"read_only":"0","write_only":"0","reinclude":0,"limit_options":"0","advanced":0,"confirmation":0,"id":5703,"options":[]},{"param_id":11,"label":"Dim Rate Adjustments (All-On\/Off Commands) ","description":"Number of steps or levels","units":"","overview":"","size":1,"bitmask":0,"default":1,"minimum":1,"maximum":99,"read_only":"0","write_only":"0","reinclude":0,"limit_options":"0","advanced":0,"confirmation":0,"id":5704,"options":[]},{"param_id":12,"label":"Dim Rate Adjustments (All-On\/Off Command, Timing)","description":"Timing of steps","units":"","overview":"","size":2,"bitmask":0,"default":3,"minimum":1,"maximum":255,"read_only":"0","write_only":"0","reinclude":0,"limit_options":"0","advanced":0,"confirmation":0,"id":5705,"options":[]}],"associations":[{"group_id":1,"label":"Lifeline","max_nodes":5,"controller":"1","description":"","overview":"","id":1869},{"group_id":2,"label":"Group 2","max_nodes":5,"controller":"0","description":"Basic Set local load","overview":"","id":1870},{"group_id":3,"label":"Group 3","max_nodes":5,"controller":"0","description":"Basic Set double click","overview":"","id":1871}],"documents":[{"id":1886,"file":"39342-HQSG-v1.pdf","label":"Manual"},{"id":1887,"file":"39339-1-x.png","label":"Image"},{"id":1888,"file":"39339.pdf","label":"Detailed Manual (EN)"}]}