{"approval_requested":0,"approved":1,"beaming":"1","database_id":18,"db_version":2,"deleted":0,"description":"15A Light Switch","device_ref":"534C:0000","exclusion":"<p>Press the switch one time to exclude it from the network.<\/p>","first_approval_time":"2018-01-20 09:01:46","frequently_listening":"0","inclusion":"<p>Press the switch one time to include it in the network.<\/p>","label":"RF9501","last_approval_time":"2018-07-22 07:20:09","listening":"1","overview":"<p>The RF9501 is a battery operated device that allows you to install a switch\/dimmer almost anywhere you desire and control (On\/Off\/Dim\/Brighten) loads\/lights wired to ASPIRE RF devices using the Associations.<\/p>","protocol_version":"3.052","routing":"1","usage":"","uuid":"rf9501","version_max":"255.255","version_min":"0.000","wakeup":"","manufacturer":{"id":5,"label":"Cooper Wiring Devices","reference":26,"uuid":"cooper","url":""},"category":{"id":21,"label":"Wall Switch","category":"WallSwitch","description":"Any device attached to the wall that controls a binary status of something, for ex. a light switch"},"endpoints":[{"id":283,"number":0,"label":"Endpoint 0","basic_class":{"id":4,"name":"BASIC_TYPE_ROUTING_SLAVE"},"generic_class":{"id":16,"name":"GENERIC_TYPE_SWITCH_BINARY"},"specific_class":{"id":3,"name":"SPECIFIC_TYPE_SCENE_SWITCH_BINARY"},"commandclass":[{"cmdclass_id":2178,"commandclass_name":"COMMAND_CLASS_NO_OPERATION","basic":"0","version":1,"nif":"","secure":"","nonsecure":"1","config":"","command_group":"MGMT","channels":[]},{"cmdclass_id":2185,"commandclass_name":"COMMAND_CLASS_BASIC","basic":"0","version":1,"nif":"","secure":"","nonsecure":"1","config":"","command_group":"APP","channels":[]},{"cmdclass_id":2180,"commandclass_name":"COMMAND_CLASS_SWITCH_BINARY","basic":"1","version":1,"nif":"0","secure":"0","nonsecure":"1","config":"","command_group":"APP","channels":[{"name":"switch_binary","config":"","label":"Switch","overview":"","deprecated":"0000-00-00","id":660,"options":[]}]},{"cmdclass_id":2177,"commandclass_name":"COMMAND_CLASS_SWITCH_ALL","basic":"0","version":1,"nif":"","secure":"","nonsecure":"1","config":"","command_group":"","channels":[]},{"cmdclass_id":2187,"commandclass_name":"COMMAND_CLASS_SCENE_ACTIVATION","basic":"0","version":1,"nif":"","secure":"","nonsecure":"1","config":"","command_group":"APP","channels":[{"name":"scene_number","config":"","label":"Scene Number","overview":"","deprecated":"0000-00-00","id":661,"options":[]}]},{"cmdclass_id":2182,"commandclass_name":"COMMAND_CLASS_CONFIGURATION","basic":"0","version":1,"nif":"","secure":"","nonsecure":"1","config":"","command_group":"APP","channels":[]},{"cmdclass_id":2176,"commandclass_name":"COMMAND_CLASS_ALARM","basic":"0","version":1,"nif":"","secure":"","nonsecure":"1","config":"","command_group":"APP","channels":[{"name":"alarm_general","config":"","label":"Alarm","overview":"","deprecated":"0000-00-00","id":659,"options":[]}]},{"cmdclass_id":2181,"commandclass_name":"COMMAND_CLASS_MANUFACTURER_SPECIFIC","basic":"0","version":1,"nif":"","secure":"","nonsecure":"1","config":"","command_group":"MGMT","channels":[]},{"cmdclass_id":2186,"commandclass_name":"COMMAND_CLASS_NODE_NAMING","basic":"0","version":1,"nif":"","secure":"","nonsecure":"1","config":"","command_group":"MGMT","channels":[]},{"cmdclass_id":2183,"commandclass_name":"COMMAND_CLASS_HAIL","basic":"0","version":1,"nif":"","secure":"","nonsecure":"1","config":"","command_group":"MGMT","channels":[]},{"cmdclass_id":2175,"commandclass_name":"COMMAND_CLASS_ASSOCIATION","basic":"0","version":1,"nif":"","secure":"","nonsecure":"1","config":"","command_group":"MGMT","channels":[]},{"cmdclass_id":2179,"commandclass_name":"COMMAND_CLASS_VERSION","basic":"0","version":1,"nif":"","secure":"","nonsecure":"1","config":"","command_group":"MGMT","channels":[]},{"cmdclass_id":2184,"commandclass_name":"COMMAND_CLASS_INDICATOR","basic":"0","version":1,"nif":"","secure":"","nonsecure":"1","config":"","command_group":"APP","channels":[]}]}],"parameters":[{"param_id":1,"label":"Delayed OFF time","description":"The time in seconds the switch will delay when trigger the delayed off feature","units":"","overview":"","size":1,"bitmask":0,"default":0,"minimum":0,"maximum":255,"read_only":"0","write_only":"0","reinclude":0,"limit_options":"0","advanced":0,"confirmation":0,"id":84,"options":[]},{"param_id":2,"label":"Panic ON time","description":"The time in seconds the switch will turn on for when panic mode is triggered","units":"","overview":"","size":1,"bitmask":0,"default":0,"minimum":0,"maximum":255,"read_only":"0","write_only":"0","reinclude":0,"limit_options":"0","advanced":0,"confirmation":0,"id":85,"options":[]},{"param_id":3,"label":"Panic OFF time","description":"The time in seconds the switch will turn off for when panic mode is triggered","units":"","overview":"","size":1,"bitmask":0,"default":0,"minimum":0,"maximum":255,"read_only":"0","write_only":"0","reinclude":0,"limit_options":"0","advanced":0,"confirmation":0,"id":86,"options":[]},{"param_id":4,"label":"Basic Set Value","description":"Value to be transmitted to devices in association group","units":"","overview":"<p>Setting this to anything other than 0 will cause the value to be transmitted to devices in the association group when the switch is triggered. A setting other than 0 will likely result in undesired operation<\/p>","size":1,"bitmask":0,"default":0,"minimum":0,"maximum":255,"read_only":"0","write_only":"0","reinclude":0,"limit_options":"0","advanced":0,"confirmation":0,"id":87,"options":[]},{"param_id":5,"label":"Power Up State","description":"Power Up State of the switch","units":"","overview":"","size":1,"bitmask":0,"default":1,"minimum":0,"maximum":255,"read_only":"","write_only":"","reinclude":0,"limit_options":"","advanced":0,"confirmation":0,"id":88,"options":[{"value":1,"label":"OFF","id":118},{"value":2,"label":"ON","id":119},{"value":3,"label":"Last State","id":120}]},{"param_id":6,"label":"Panic mode enable","description":"Enables this switch to participate in panic mode","units":"","overview":"","size":1,"bitmask":0,"default":1,"minimum":0,"maximum":255,"read_only":"","write_only":"","reinclude":0,"limit_options":"","advanced":0,"confirmation":0,"id":89,"options":[{"value":1,"label":"OFF","id":121},{"value":2,"label":"ON","id":122}]}],"associations":[{"group_id":1,"label":"Group 1","max_nodes":5,"controller":"1","description":"","overview":"","id":28}],"documents":[{"id":197,"file":"AspireRFSwitchSpecSheet.pdf","label":"Specification Sheet"},{"id":1217,"file":"RF9501.jpg","label":"Product Image"}]}